boxes_classifier/__init__.py
boxes_classifier/api.py
boxes_classifier/boxes_classifier_cli.py
boxes_classifier/core/__init__.py
boxes_classifier/core/config.py
boxes_classifier/core/datasets.py
boxes_classifier/core/embedding.py
boxes_classifier/core/inference.py
boxes_classifier/core/inference_with_torch.py
boxes_classifier/core/sync_image.py
boxes_classifier/core/train.py
boxes_classifier/core/train_with_pytorch.py
boxes_classifier/core/utils.py
boxes_classifier/data/model/embeddings/part-000.parquet
boxes_classifier-1.0.4.dist-info/LICENSE.txt
boxes_classifier-1.0.4.dist-info/METADATA
boxes_classifier-1.0.4.dist-info/WHEEL
boxes_classifier-1.0.4.dist-info/entry_points.txt
boxes_classifier-1.0.4.dist-info/top_level.txt
boxes_classifier-1.0.4.dist-info/RECORD
